<?xml version="1.0" encoding="UTF-8"?>
<!DOCTYPE mapper PUBLIC "-//mybatis.org//DTD Mapper 3.0//EN" "http://mybatis.org/dtd/mybatis-3-mapper.dtd">

<mapper namespace="leiren.haozhaojob.modules.operation.dao.EnchashmentBindingCheckDao">

	<!-- 可根据自己的需求，是否要使用 -->
    <resultMap type="leiren.haozhaojob.modules.operation.entity.EnchashmentBindingCheckEntity" id="enchashmentBindingCheckMap">
        <result property="id" column="id"/>
        <result property="objectType" column="object_type"/>
        <result property="objectId" column="object_id"/>
        <result property="isDefault" column="is_default"/>
        <result property="enchashmentType" column="enchashment_type"/>
        <result property="account" column="account"/>
        <result property="bank" column="bank"/>
        <result property="bankName" column="bank_name"/>
        <result property="realName" column="real_name"/>
        <result property="subbranch" column="subbranch"/>
        <result property="accountName" column="account_name"/>
        <result property="bankUnionId" column="bank_union_id"/>
        <result property="status" column="status"/>
        <result property="remark" column="remark"/>
    </resultMap>
</mapper>
